README.md
setup.py
qed_seal.egg-info/PKG-INFO
qed_seal.egg-info/SOURCES.txt
qed_seal.egg-info/dependency_links.txt
qed_seal.egg-info/entry_points.txt
qed_seal.egg-info/requires.txt
qed_seal.egg-info/top_level.txt
seal/__init__.py
seal/seal.py
seal/watermark.py
seal/watermark/qed-logo-1c-rev.png
seal/watermark/qed-logo-1c.png
seal/watermark/qed-logo-byline-1c-rev.png
seal/watermark/qed-logo-byline-1c.png
seal/watermark/qed-logo-byline-rev.png
seal/watermark/qed-logo-byline.png
seal/watermark/qed-logo-rev.png
seal/watermark/qed-logo-square-1c-rev.png
seal/watermark/qed-logo-square-1c.png
seal/watermark/qed-logo-square-rev.png
seal/watermark/qed-logo-square.png
seal/watermark/qed-logo.png