Metadata-Version: 1.2
Name: qed-seal
Version: 0.4
Summary: image watermarking tool
Home-page: https://github.com/qedsoftware/seal
Author: QED
Author-email: software@qed.ai
License: MIT
Keywords: watermark seal qed
Platform: UNKNOWN
Classifier: Programming Language :: Python :: 3
Requires-Python: >=3
